{
  "app": "Warriors of Christ",
  "date": "2026-07-05",
  "provider": "groq",
  "model": "llama-3.1-8b-instant",
  "max_tokens": 500,
  "temperature": 0.7,
  "words": 178,
  "content_markdown": "# Unshakeable Foundation\n## Scripture\n\"Everyone then who hears these words of mine and does them will be like a wise man who built his house on the rock. And the rain fell, and the floods came, and the winds blew and beat on that house, but it did not fall, because it had been founded on the rock.\" – Matthew 7:24-25\n## Reflection\nAs men, we face many challenges in life - some of them seemingly insurmountable. But we must not let fear or uncertainty shake our foundation. Jesus taught us that when we build our lives on the rock of His word, we can withstand even the toughest storms. This foundation is based on faith, trust, and obedience to God's commands. When we prioritize our relationship with Him, we can confidently stand firm in the midst of turmoil. In a world that is constantly trying to undermine our faith, we must anchor ourselves in His word and trust in His sovereignty.\n\n## Daily Challenge\n\"Run 5 miles while praying for strength and guidance in uncertain times.\""
}